qtlib/__init__.py
qtlib-0.0.2.dist-info/LICENSE
qtlib-0.0.2.dist-info/METADATA
qtlib-0.0.2.dist-info/WHEEL
qtlib-0.0.2.dist-info/top_level.txt
qtlib-0.0.2.dist-info/RECORD
